senpy/VERSION
senpy/__init__.py
senpy/__main__.py
senpy/api.py
senpy/blueprints.py
senpy/cli.py
senpy/client.py
senpy/config.py
senpy/extensions.py
senpy/gsitk_compat.py
senpy/meta.py
senpy/models.py
senpy/testing.py
senpy/utils.py
senpy/version.py
senpy/plugins/__init__.py
senpy/plugins/base/misc/__init__.py
senpy/plugins/base/misc/split_plugin.py
senpy/plugins/base/postprocessing/__init__.py
senpy/plugins/base/postprocessing/emotion/__init__.py
senpy/plugins/base/postprocessing/emotion/centroids.py
senpy/plugins/base/postprocessing/emotion/ekman2fsre.senpy
senpy/plugins/base/postprocessing/emotion/ekman2vad.senpy
senpy/plugins/base/postprocessing/emotion/maxEmotion_plugin.py
senpy/plugins/default/sentiment/meaningcloud_plugin.py
senpy/plugins/default/sentiment/sentiment140_plugin.py
senpy/plugins/default/sentiment/vader/README.md
senpy/plugins/default/sentiment/vader/vaderSentiment.py
senpy/plugins/default/sentiment/vader/vader_plugin.py
senpy/plugins/default/sentiment/vader/vader_sentiment_lexicon.txt
senpy/plugins/optional/emotion/depechemood_plugin.py
senpy/plugins/optional/emotion/anew/README.md
senpy/plugins/optional/emotion/anew/emotion-anew.py
senpy/plugins/optional/emotion/anew/emotion-anew.senpy
senpy/plugins/optional/emotion/wnaffect/Dockerfile.template
senpy/plugins/optional/emotion/wnaffect/Makefile
senpy/plugins/optional/emotion/wnaffect/README.md
senpy/plugins/optional/emotion/wnaffect/emotion-wnaffect.py
senpy/plugins/optional/emotion/wnaffect/emotion-wnaffect.senpy
senpy/plugins/optional/emotion/wnaffect/emotion.py
senpy/plugins/optional/emotion/wnaffect/wnaffect.py
senpy/plugins/optional/sentiment/basic/README.md
senpy/plugins/optional/sentiment/basic/sentiment-basic.py
senpy/plugins/optional/sentiment/basic/sentiment-basic.senpy
senpy/plugins/optional/sentiment/basic/sentiwn.py
senpy/schemas/aggregatedEvaluation.json
senpy/schemas/analysis.json
senpy/schemas/atom.json
senpy/schemas/context.json
senpy/schemas/context.jsonld
senpy-1.1.0.dist-info/LICENSE.txt
senpy-1.1.0.dist-info/METADATA
senpy-1.1.0.dist-info/WHEEL
senpy-1.1.0.dist-info/entry_points.txt
senpy-1.1.0.dist-info/top_level.txt
senpy-1.1.0.dist-info/RECORD
