Metadata-Version: 2.1
Name: senpy
Version: 1.1.0
Summary: A sentiment analysis server implementation. Designed to be extensible, so new algorithms and sources can be used.
Home-page: https://github.com/gsi-upm/senpy
Download-URL: https://github.com/gsi-upm/senpy/archive/1.1.0.tar.gz
Author: J. Fernando Sanchez
Author-email: balkian@gmail.com
Keywords: eurosentiment,sentiment,emotions,nif
Classifier: Programming Language :: Python :: 3
Requires-Python: >3.6
License-File: LICENSE.txt
Requires-Dist: Flask >=0.10.1
Requires-Dist: requests >=2.4.1
Requires-Dist: tornado >=4.4.3
Requires-Dist: PyLD >=0.6.5
Requires-Dist: nltk
Requires-Dist: future
Requires-Dist: jsonschema
Requires-Dist: jsonref
Requires-Dist: PyYAML
Requires-Dist: rdflib ==6.1.1
Requires-Dist: numpy
Requires-Dist: scipy
Requires-Dist: scikit-learn >=0.20
Requires-Dist: responses
Requires-Dist: jmespath
Provides-Extra: evaluation
Requires-Dist: gsitk >0.1.9.1 ; extra == 'evaluation'
Requires-Dist: flask-cors ==3.0.10 ; extra == 'evaluation'
Requires-Dist: Pattern ==3.6 ; extra == 'evaluation'
Requires-Dist: lxml ==4.9.3 ; extra == 'evaluation'
Requires-Dist: pandas ==2.1.1 ; extra == 'evaluation'
Requires-Dist: textblob ==0.17.1 ; extra == 'evaluation'
Provides-Extra: extras
Requires-Dist: gsitk >0.1.9.1 ; extra == 'extras'
Requires-Dist: flask-cors ==3.0.10 ; extra == 'extras'
Requires-Dist: Pattern ==3.6 ; extra == 'extras'
Requires-Dist: lxml ==4.9.3 ; extra == 'extras'
Requires-Dist: pandas ==2.1.1 ; extra == 'extras'
Requires-Dist: textblob ==0.17.1 ; extra == 'extras'
